pyorbs/__init__.py
pyorbs/__main__.py
pyorbs/orb.py
pyorbs/py.typed
pyorbs/requirements.py
pyorbs/shell.py
pyorbs/templates.py
pyorbs/templates/activate_orb.bash
pyorbs/templates/activate_orb.fish
pyorbs/templates/lockfile_header
pyorbs/templates/orb-completion.bash
pyorbs-2.1.1.dist-info/LICENSE.txt
pyorbs-2.1.1.dist-info/METADATA
pyorbs-2.1.1.dist-info/WHEEL
pyorbs-2.1.1.dist-info/entry_points.txt
pyorbs-2.1.1.dist-info/top_level.txt
pyorbs-2.1.1.dist-info/RECORD
