Metadata-Version: 2.2
Name: pyorbs
Version: 2.1.1
Summary: A tool for managing Python virtual environments
Author-email: Logikal GmbH <contact@logikal.io>
License: | Copyright 2019 Webrepublic AG
Project-URL: Documentation, https://docs.logikal.io/pyorbs/
Project-URL: Release notes, https://github.com/logikal-io/pyorbs/releases
Project-URL: Issue tracker, https://github.com/logikal-io/pyorbs/issues
Project-URL: Source code, https://github.com/logikal-io/pyorbs
Keywords: development,virtual environment
Classifier: Development Status :: 5 - Production/Stable
Classifier: Intended Audience :: Developers
Classifier: License :: OSI Approved :: MIT License
Classifier: Operating System :: POSIX :: Linux
Classifier: Programming Language :: Python :: 3
Classifier: Programming Language :: Python :: 3.12
Classifier: Environment :: Console
Classifier: Topic :: Software Development
Classifier: Topic :: Utilities
Classifier: Typing :: Typed
Requires-Python: ~=3.12
License-File: LICENSE.txt
